awslabs/__init__.py
awslabs/cloudwatch_mcp_server/__init__.py
awslabs/cloudwatch_mcp_server/aws_common.py
awslabs/cloudwatch_mcp_server/common.py
awslabs/cloudwatch_mcp_server/server.py
awslabs/cloudwatch_mcp_server/cloudwatch_alarms/models.py
awslabs/cloudwatch_mcp_server/cloudwatch_alarms/tools.py
awslabs/cloudwatch_mcp_server/cloudwatch_logs/models.py
awslabs/cloudwatch_mcp_server/cloudwatch_logs/tools.py
awslabs/cloudwatch_mcp_server/cloudwatch_metrics/cloudformation_template_generator.py
awslabs/cloudwatch_mcp_server/cloudwatch_metrics/constants.py
awslabs/cloudwatch_mcp_server/cloudwatch_metrics/metric_analyzer.py
awslabs/cloudwatch_mcp_server/cloudwatch_metrics/metric_data_decomposer.py
awslabs/cloudwatch_mcp_server/cloudwatch_metrics/models.py
awslabs/cloudwatch_mcp_server/cloudwatch_metrics/tools.py
cloudwatch_mcp_multiprofile-0.1.0.dist-info/LICENSE
cloudwatch_mcp_multiprofile-0.1.0.dist-info/METADATA
cloudwatch_mcp_multiprofile-0.1.0.dist-info/NOTICE
cloudwatch_mcp_multiprofile-0.1.0.dist-info/WHEEL
cloudwatch_mcp_multiprofile-0.1.0.dist-info/entry_points.txt
cloudwatch_mcp_multiprofile-0.1.0.dist-info/top_level.txt
cloudwatch_mcp_multiprofile-0.1.0.dist-info/RECORD
