Metadata-Version: 2.2
Name: cloudwatch-mcp-multiprofile
Version: 0.1.0
Summary: CloudWatch MCP Server with Multi-Profile Support - Fork of awslabs.cloudwatch-mcp-server
Author: Amazon Web Services
Author-email: Avraham Yom-Tov <avraham.yom-tov@nice.com>
Project-URL: homepage, https://github.com/Avri-Here/awsMcpfix
Project-URL: repository, https://github.com/Avri-Here/awsMcpfix
Project-URL: Original Project, https://github.com/awslabs/mcp
Project-URL: Pull Request, https://github.com/awslabs/mcp/pull/1950
Keywords: mcp,cloudwatch,aws,multi-profile,observability
Classifier: Operating System :: OS Independent
Classifier: Programming Language :: Python
Classifier: Programming Language :: Python :: 3
Classifier: Programming Language :: Python :: 3.10
Classifier: Programming Language :: Python :: 3.11
Classifier: Programming Language :: Python :: 3.12
Classifier: Programming Language :: Python :: 3.13
Requires-Python: >=3.10
License-File: LICENSE
License-File: NOTICE
Requires-Dist: boto3>=1.38.22
Requires-Dist: loguru>=0.7.0
Requires-Dist: mcp[cli]>=1.23.0
Requires-Dist: pydantic>=2.10.6
Requires-Dist: numpy>=2.0.0
Requires-Dist: pandas>=2.2.3
Requires-Dist: statsmodels>=0.14.0
